src/__init__.py
src/__main__.py
src/config.py
src/cshell.py
src/cutils.py
src/interpreter.py
src/output_formatter.py
src/sqlite.py
src/template.py
src/timer.py
eichhoernchen-2.2.dist-info/LICENSE
eichhoernchen-2.2.dist-info/METADATA
eichhoernchen-2.2.dist-info/WHEEL
eichhoernchen-2.2.dist-info/entry_points.txt
eichhoernchen-2.2.dist-info/top_level.txt
eichhoernchen-2.2.dist-info/RECORD
