Metadata-Version: 2.1
Name: eichhoernchen
Version: 2.2
Summary: Lightweight curses-based time tracking tool.
Home-page: https://github.com/pascalinde/eichhoernchen
Author: Carine Dengler
Author-email: eichhoernchen@pascalin.de
License: UNKNOWN
Platform: UNKNOWN
Classifier: License :: OSI Approved :: GNU General Public License v3 (GPLv3)
Classifier: Operating System :: POSIX :: Linux
Classifier: Programming Language :: Python :: 3.7
Classifier: Programming Language :: Python :: 3.8
Classifier: Programming Language :: Python :: 3.9
